wechat_agent/SysEnum.py
wechat_agent/__about__.py
wechat_agent/__init__.py
wechat_agent/conf.py
wechat_agent/logger_config.py
wechat_agent/main.py
wechat_agent/nav.json
wechat_agent/controller/agent_controller.py
wechat_agent/controller/ai_role_controller.py
wechat_agent/controller/auth_controller.py
wechat_agent/controller/base_controller.py
wechat_agent/controller/history_controller.py
wechat_agent/controller/model_controller.py
wechat_agent/controller/reply_controller.py
wechat_agent/controller/service_error.py
wechat_agent/domain/ajax_result.py
wechat_agent/service/captcha_util.py
wechat_agent/service/db_util.py
wechat_agent/service/jwt_util.py
wechat_agent/service/langchain_util.py
wechat_agent/service/md5_util.py
wechat_agent/service/receive.py
wechat_agent/service/send.py
wechat_agent/service/systemInfo_util.py
wechat_agent/service/wx_util.py
wechat_agent/service/wxauto3_util.py
wechat_agent/service/wxauto4_util.py
wechat_agent/ui/favicon.ico
wechat_agent/ui/index.html
wechat_agent/ui/css/app.b8fac6ca.css
wechat_agent/ui/css/chunk-09c06fed.2f216e2d.css
wechat_agent/ui/css/chunk-262d3217.4e434419.css
wechat_agent/ui/css/chunk-2add76c4.99be8bbf.css
wechat_agent/ui/css/chunk-2d8425c6.7ec87c98.css
wechat_agent/ui/css/chunk-302b5b3a.16f6bedb.css
wechat_agent/ui/css/chunk-3a451b30.a3fab039.css
wechat_agent/ui/css/chunk-5f818cec.dfdde5e4.css
wechat_agent/ui/css/chunk-a315c34e.e7ed4d9f.css
wechat_agent/ui/css/chunk-e0d753da.6fec90e3.css
wechat_agent/ui/css/chunk-vendors.8fa15813.css
wechat_agent/ui/fonts/element-icons.535877f5.woff
wechat_agent/ui/fonts/element-icons.732389de.ttf
wechat_agent/ui/img/login-background.f9f49138.jpg
wechat_agent/ui/js/app.85787526.js
wechat_agent/ui/js/app.85787526.js.map
wechat_agent/ui/js/chunk-09c06fed.5a28cd6a.js
wechat_agent/ui/js/chunk-09c06fed.5a28cd6a.js.map
wechat_agent/ui/js/chunk-262d3217.00c44ccc.js
wechat_agent/ui/js/chunk-262d3217.00c44ccc.js.map
wechat_agent/ui/js/chunk-2add76c4.4c0427c8.js
wechat_agent-0.0.5.dist-info/METADATA
wechat_agent-0.0.5.dist-info/WHEEL
wechat_agent-0.0.5.dist-info/entry_points.txt
wechat_agent-0.0.5.dist-info/licenses/LICENSE.txt
wechat_agent-0.0.5.dist-info/RECORD
